ucla_geotech_tools_response_spectrum-1.0.5-py3.9-nspkg.pth
ucla_geotech_tools/response_spectrum.cp39-win_amd64.pyd
ucla_geotech_tools_response_spectrum-1.0.5.dist-info/METADATA
ucla_geotech_tools_response_spectrum-1.0.5.dist-info/WHEEL
ucla_geotech_tools_response_spectrum-1.0.5.dist-info/namespace_packages.txt
ucla_geotech_tools_response_spectrum-1.0.5.dist-info/top_level.txt
ucla_geotech_tools_response_spectrum-1.0.5.dist-info/RECORD
