Metadata-Version: 2.1
Name: ucla-geotech-tools-response-spectrum
Version: 1.0.5
Summary: Python package for computing acceleration response spectra.
Home-page: UNKNOWN
Author: Scott J. Brandenberg
Author-email: sjbrandenberg@ucla.edu
License: UNKNOWN
Platform: UNKNOWN
